purplship/mappers/canadapost/__init__.py
purplship/mappers/canadapost/mapper.py
purplship/mappers/canadapost/proxy.py
purplship/mappers/canadapost/settings.py
purplship/providers/canadapost/__init__.py
purplship/providers/canadapost/error.py
purplship/providers/canadapost/pickup/__init__.py
purplship/providers/canadapost/pickup/cancel.py
purplship/providers/canadapost/pickup/create.py
purplship/providers/canadapost/pickup/update.py
purplship/providers/canadapost/rate.py
purplship/providers/canadapost/shipment/__init__.py
purplship/providers/canadapost/shipment/cancel.py
purplship/providers/canadapost/shipment/contract.py
purplship/providers/canadapost/shipment/create.py
purplship/providers/canadapost/shipment/non_contract.py
purplship/providers/canadapost/tracking.py
purplship/providers/canadapost/units.py
purplship/providers/canadapost/utils.py
purplship.canadapost-2022.2.1.dist-info/WHEEL
purplship.canadapost-2022.2.1.dist-info/METADATA
purplship.canadapost-2022.2.1.dist-info/RECORD
